itk_montage-0.8.5.dist-info/RECORD
itk_montage-0.8.5.dist-info/WHEEL
itk_montage-0.8.5.dist-info/METADATA
itk_montage-0.8.5.dist-info/licenses/LICENSE
itk_montage.libs/libtbb-3c88584c.so.12.9
itk/itkPhaseCorrelationImageRegistrationMethodPython.py
itk/itkNMinimaMaximaImageCalculatorPython.py
itk/MontagePython.py
itk/itkTileMontagePython.py
itk/itkPhaseCorrelationOperatorPython.py
itk/_MontagePython.cpython-310-x86_64-linux-gnu.so
itk/itkTileConfigurationPython.py
itk/itkTileMergeImageFilterPython.py
itk/itkPhaseCorrelationOptimizerPython.py
itk/Configuration/Montage_snake_case.py
itk/Configuration/MontageConfig.py
