Metadata-Version: 2.1
Name: itk-montage
Version: 0.8.5
Summary: Montaging for microscopy imaging files.
Keywords: itk,InsightToolkit
Author-Email: =?utf-8?b?RMW+ZW5hbiBadWtpxIc=?= <dzenan.zukic@kitware.com>, Matt McCormick <matt.mccormick@kitware.com>
License:                                  Apache License
Classifier: Development Status :: 4 - Beta
Classifier: Intended Audience :: Developers
Classifier: Intended Audience :: Education
Classifier: Intended Audience :: Healthcare Industry
Classifier: Intended Audience :: Science/Research
Classifier: License :: OSI Approved :: Apache Software License
Classifier: Operating System :: Android
Classifier: Operating System :: MacOS
Classifier: Operating System :: Microsoft :: Windows
Classifier: Operating System :: POSIX
Classifier: Operating System :: Unix
Classifier: Programming Language :: C++
Classifier: Programming Language :: Python
Classifier: Topic :: Scientific/Engineering
Classifier: Topic :: Scientific/Engineering :: Information Analysis
Classifier: Topic :: Scientific/Engineering :: Medical Science Apps.
Classifier: Topic :: Software Development :: Libraries
Project-URL: Download, https://github.com/InsightSoftwareConsortium/ITKMontage
Project-URL: Homepage, https://github.com/InsightSoftwareConsortium/ITKMontage
Requires-Python: >=3.9
Requires-Dist: itk-core>=5.4.2
Requires-Dist: itk-filtering>=5.4.2
Requires-Dist: itk-io>=5.4.2
Requires-Dist: numpy
